大二上/数字逻辑与数字系统/用verilog实现的作业和加分作业/bonus 3/3.16.v
`timescale 10ps/1ps

module Verilog1(CLK,Q1,Q2,Q3);
    input CLK;
    output Q1,Q2,Q3;
    reg Q1,Q2,Q3;
    always @(posedge CLK) begin
        Q1<=(~Q3)|(~Q2&Q1);
        Q2<=(Q2&Q1)|(~Q2&~Q1)|(~Q3&Q1);
        Q3<=Q2;
    end
    initial begin
        Q1<=1;
        Q2<=0;
        Q3<=0;
        $dumpfile("3.16.vcd");
        $dumpvars(0,Verilog1);
    end
endmodule

module Verilog1_tb;
    reg c;
    wire q1,q2,q3;
    integer i;
    Verilog1 Verilog1(.Q1(q1),.Q2(q2),.Q3(q3),.CLK(c));
    initial begin
        c<=0;
        for(i=0;i<8;i=i+1)begin
        #10 c<=1;
        #10 c<=0;
        end
        #10 $finish;
    end
endmodule

大二上/数字逻辑与数字系统/用verilog实现的作业和加分作业/bonus 3/3.16.vcd
$date
	Sun Nov 24 17:20:15 2024
$end
$version
	Icarus Verilog
$end
$timescale
	1ps
$end
$scope module Verilog1_tb $end
$scope module Verilog1 $end
$var wire 1 ! CLK $end
$var reg 1 " Q1 $end
$var reg 1 # Q2 $end
$var reg 1 $ Q3 $end
$upscope $end
$upscope $end
$enddefinitions $end
$comment Show the parameter values. $end
$dumpall
$end
#0
$dumpvars
0$
0#
1"
0!
$end
#100
1#
1!
#200
0!
#300
1$
1!
#400
0!
#500
0"
1!
#600
0!
#700
0#
1!
#800
0!
#900
0$
1#
1!
#1000
0!
#1100
1$
0#
1"
1!
#1200
0!
#1300
0$
1!
#1400
0!
#1500
1#
1!
