大二上/数字逻辑与数字系统/用verilog实现的作业和加分作业/bonus 1/3.1.v
`timescale 10ps/1ps

module Verilog1(A,B,C,Y);
input A,B,C;
output Y;
reg Y;

always @(A, B, C) begin
        Y<=((~B)|(~C)|(A&Y));
end

initial begin
    Y<= 1;
    $dumpfile("3.1.vcd");
    $dumpvars(0,Verilog1);
end
endmodule

module Verilog1_tb;
reg aa,bb,cc;
wire yy;
Verilog1 Verilog1(.A(aa),.B(bb),.C(cc),.Y(yy));
initial begin
        aa<=1;
        bb<=1;
        cc<=1;
    #10 aa<=0;
    #10 aa<=1;
    #5  bb<=0;
    #5  cc<=0;
    #5  bb<=1;
    #5  cc<=1;
    #5  bb<=0;
    #10 bb<=1;
    #10 aa<=0;
    #10 aa<=1;
    #5  cc<=0;
    #10 $finish;
end
endmodule

大二上/数字逻辑与数字系统/用verilog实现的作业和加分作业/bonus 1/3.1.vcd
$date
	Sun Nov 24 15:13:17 2024
$end
$version
	Icarus Verilog
$end
$timescale
	1ps
$end
$scope module Verilog1_tb $end
$scope module Verilog1 $end
$var wire 1 ! A $end
$var wire 1 " B $end
$var wire 1 # C $end
$var reg 1 $ Y $end
$upscope $end
$upscope $end
$enddefinitions $end
$comment Show the parameter values. $end
$dumpall
$end
#0
$dumpvars
1$
1#
1"
1!
$end
#100
0$
0!
#200
1!
#250
1$
0"
#300
0#
#350
1"
#400
1#
#450
0"
#550
1"
#650
0$
0!
#750
1!
#800
1$
0#
