大二上/数字逻辑与数字系统/用verilog实现的作业和加分作业/bonus 1/3.3.v
`timescale 10ps/1ps

module Verilog1(J,K,CLK,Q);
    input J,K,CLK;
    output Q;
    reg Q;
    always @(negedge CLK) begin
        Q <=((J&(~Q))|((~K)&Q));
    end
    initial begin
        Q<= 0;
        $dumpfile("3.3.vcd");
        $dumpvars(0,Verilog1);
    end
endmodule

module Verilog1_tb;
    reg j,k,c;
    wire q;
    Verilog1 Verilog1(.J(j),.K(k),.CLK(c),.Q(q));
    initial begin
        c<=0;
        forever
            #10 c=~c;
    end
    initial begin
        j<=0;
        k<=0;
        #15 j=1;
        #6 j=0;
        #4 j=1;
        k=1;
        #30 k=0;
        #10 j=0;
        #2 k=1;
        #8 k=0;
        #10 k=1;
        #8 j=1;
        #2 j=0;
        #14 k=0;
        #2 k=1;
        #2 k=0;
        #10 $finish;
    end
endmodule

大二上/数字逻辑与数字系统/用verilog实现的作业和加分作业/bonus 1/3.3.vcd
$date
	Sun Nov 24 15:26:43 2024
$end
$version
	Icarus Verilog
$end
$timescale
	1ps
$end
$scope module Verilog1_tb $end
$scope module Verilog1 $end
$var wire 1 ! CLK $end
$var wire 1 " J $end
$var wire 1 # K $end
$var reg 1 $ Q $end
$upscope $end
$upscope $end
$enddefinitions $end
$comment Show the parameter values. $end
$dumpall
$end
#0
$dumpvars
0$
0#
0"
0!
$end
#100
1!
#150
1"
#200
1$
0!
#210
0"
#250
1#
1"
#300
1!
#400
0$
0!
#500
1!
#550
0#
#600
1$
0!
#650
0"
#670
1#
#700
1!
#750
0#
#800
0!
#850
1#
#900
1!
#930
1"
#950
0"
#1000
0$
0!
#1090
0#
#1100
1!
#1110
1#
#1130
0#
