大二上/数字逻辑与数字系统/用verilog实现的作业和加分作业/bonus 1/3.5.v
`timescale 10ps/1ps

module Verilog1(CLK,Q1,Q2,Q3,Q4);
    input CLK;
    output Q1,Q2,Q3,Q4;
    reg Q1,Q2,Q3,Q4;
    always @(posedge CLK) begin
        Q1<=Q1;
        Q2<=0;
        Q3<=~Q3;
    end
    always @(negedge CLK) begin
        Q4<=~Q4;
    end
    initial begin
        Q1<=0;
        Q2<=0;
        Q3<=0;
        Q4<=0;
        $dumpfile("3.5.vcd");
        $dumpvars(0,Verilog1);
    end
endmodule

module Verilog1_tb;
    reg c;
    wire q1,q2,q3,q4;
    Verilog1 Verilog1(.Q1(q1),.Q2(q2),.Q3(q3),.Q4(q4),.CLK(c));
    initial begin
        c<=0;
        #10 c<=1;
        #10 c<=0;
        #10 c<=1;
        #10 c<=0;
        #10 c<=1;
        #10 c<=0;
        #10 c<=1;
        #10 c<=0;
        #10 c<=1;
        #10 c<=0;
        #10 $finish;
    end
endmodule

大二上/数字逻辑与数字系统/用verilog实现的作业和加分作业/bonus 1/3.5.vcd
$date
	Sun Nov 24 16:28:38 2024
$end
$version
	Icarus Verilog
$end
$timescale
	1ps
$end
$scope module Verilog1_tb $end
$scope module Verilog1 $end
$var wire 1 ! CLK $end
$var reg 1 " Q1 $end
$var reg 1 # Q2 $end
$var reg 1 $ Q3 $end
$var reg 1 % Q4 $end
$upscope $end
$upscope $end
$enddefinitions $end
$comment Show the parameter values. $end
$dumpall
$end
#0
$dumpvars
1%
0$
0#
0"
0!
$end
#100
1$
1!
#200
0%
0!
#300
0$
1!
#400
1%
0!
#500
1$
1!
#600
0%
0!
#700
0$
1!
#800
1%
0!
#900
1$
1!
#1000
0%
0!
